myinfo/__init__.py
myinfo/ip_info.py
myinfo/whois_info.py
myinfo-1.1.1.dist-info/METADATA
myinfo-1.1.1.dist-info/WHEEL
myinfo-1.1.1.dist-info/top_level.txt
myinfo-1.1.1.dist-info/RECORD
