Metadata-Version: 2.1
Name: myinfo
Version: 1.1.1
Summary: A package to retrieve WHOIS and IP information
Author: MrFidal
Author-email: mrfidal@proton.me
Requires-Python: >=3.6
Requires-Dist: whois
Requires-Dist: ipwhois
Requires-Dist: dnspython
